<?xml version="1.0" encoding="utf-8" ?>
<dwsync>
<file name="music01_gbout.m4a" server="C:/Program Files (x86)/Apache Software Foundation/Tomcat 9.0/webapps/ROOT/charcnt" local="132031304754346112" remote="132031304750000000" Dst="0" />
<file name="music01_gbout.m4a" server="C:/Program Files (x86)/Apache Software Foundation/Tomcat 9.0/webapps/ROOT/charcnt/" local="132031304754346112" remote="132031304750000000" Dst="0" />
<file name="music02_gbout.m4a" server="C:/Program Files (x86)/Apache Software Foundation/Tomcat 9.0/webapps/ROOT/charcnt/" local="132031340290202624" remote="132031340290000000" Dst="0" />
<file name="music03_gbout.m4a" server="C:/Program Files (x86)/Apache Software Foundation/Tomcat 9.0/webapps/ROOT/charcnt/" local="132031349823966720" remote="132031349820000000" Dst="0" />
<file name="music04_gbout.m4a" server="C:/Program Files (x86)/Apache Software Foundation/Tomcat 9.0/webapps/ROOT/charcnt/" local="132031354870801920" remote="132031354870000000" Dst="0" />
<file name="music05_gbout.m4a" server="C:/Program Files (x86)/Apache Software Foundation/Tomcat 9.0/webapps/ROOT/charcnt/" local="132031359649295360" remote="132031359640000000" Dst="0" />
<file name="Ring05.wav" server="C:/Program Files (x86)/Apache Software Foundation/Tomcat 9.0/webapps/ROOT/charcnt/" local="131814701012137660" remote="131814701010000000" Dst="0" />
<file name="voice01.mp3" server="C:/Program Files (x86)/Apache Software Foundation/Tomcat 9.0/webapps/ROOT/charcnt/" local="132030875085393260" remote="132030875080000000" Dst="0" />
</dwsync>